{
  "po" : 
  {
    "en_US" : 
    {
      "branch" : "",
      "commit" : 
      {
        "date" : "",
        "hash" : "",
        "title" : ""
      }
    },
    "zh_CN" : 
    {
      "branch" : "main",
      "commit" : 
      {
        "date" : "2026-04-05 19:50:49 -0600",
        "hash" : "8203da6e4cdad722664fa740c7a9514104483f07",
        "title" : "TYP: ``tile``: accept numpy scalars and arrays as second argument (#31161)"
      }
    },
    "zh_TW" : 
    {
      "branch" : "main",
      "commit" : 
      {
        "date" : "2026-04-05 19:50:49 -0600",
        "hash" : "8203da6e4cdad722664fa740c7a9514104483f07",
        "title" : "TYP: ``tile``: accept numpy scalars and arrays as second argument (#31161)"
      }
    }
  },
  "pot" : 
  {
    "branch" : "main",
    "commit" : 
    {
      "date" : "2026-04-05 19:50:49 -0600",
      "hash" : "8203da6e4cdad722664fa740c7a9514104483f07",
      "title" : "TYP: ``tile``: accept numpy scalars and arrays as second argument (#31161)"
    }
  },
  "type" : "branch",
  "version" : "main"
}